causalforge/__init__.py
causalforge/tests/__init__.py
causalforge-0.0.1.dist-info/LICENSE
causalforge-0.0.1.dist-info/METADATA
causalforge-0.0.1.dist-info/WHEEL
causalforge-0.0.1.dist-info/top_level.txt
causalforge-0.0.1.dist-info/RECORD
