Metadata-Version: 2.1
Name: causalforge
Version: 0.0.1
Summary: Python Package for Causal Inference
Home-page: https://gitlab.com/gtesei/causalFlow
Author: Gino Tesei, Jey Kottalam
Author-email: 
Classifier: Programming Language :: Python
Classifier: License :: OSI Approved :: Apache Software License
Classifier: Operating System :: OS Independent
Requires-Python: >=3.7
License-File: LICENSE
Requires-Dist: setuptools
Requires-Dist: pip (>=10.0)
Requires-Dist: numpy (>=1.18.5)
Requires-Dist: scipy (>=1.4.1)
Requires-Dist: matplotlib
Requires-Dist: pandas (>=0.24.1)
Requires-Dist: scikit-learn
Requires-Dist: statsmodels
Requires-Dist: seaborn
Requires-Dist: Cython
Requires-Dist: tqdm
Requires-Dist: torch
Requires-Dist: docutils
